adafruit_ds248x.py
adafruit_circuitpython_ds248x-1.2.5.dist-info/licenses/LICENSE
adafruit_circuitpython_ds248x-1.2.5.dist-info/METADATA
adafruit_circuitpython_ds248x-1.2.5.dist-info/WHEEL
adafruit_circuitpython_ds248x-1.2.5.dist-info/top_level.txt
adafruit_circuitpython_ds248x-1.2.5.dist-info/RECORD
