Metadata-Version: 2.4
Name: adafruit-circuitpython-ds248x
Version: 1.2.5
Summary: CircuitPython driver for the DS2484 I2C to 1-Wire Bus Adapter
Author-email: Adafruit Industries <circuitpython@adafruit.com>
License: MIT
Project-URL: Homepage, https://github.com/adafruit/Adafruit_CircuitPython_DS248x
Keywords: adafruit,blinka,circuitpython,micropython,ds248x,OneWire,,DS18B20
Classifier: Intended Audience :: Developers
Classifier: Topic :: Software Development :: Libraries
Classifier: Topic :: Software Development :: Embedded Systems
Classifier: Topic :: System :: Hardware
Classifier: License :: OSI Approved :: MIT License
Classifier: Programming Language :: Python :: 3
License-File: LICENSE
Requires-Dist: Adafruit-Blinka
Requires-Dist: adafruit-circuitpython-busdevice
Provides-Extra: optional
Dynamic: license-file
